{
    "data": {
        "elements": {
            "0ef49b6e-bdcc-424f-9776-f97eed894cf4": {
                "data": {
                    "aabb": {
                        "data": {
                            "frame": {
                                "point": [
                                    0.0,
                                    0.0,
                                    -2.7755575615628914e-17
                                ],
                                "xaxis": [
                                    1.0,
                                    0.0,
                                    0.0
                                ],
                                "yaxis": [
                                    0.0,
                                    1.0,
                                    0.0
                                ]
                            },
                            "xsize": 1.6329931618554523,
                            "ysize": 1.6329931618554523,
                            "zsize": 1.1547005383792517
                        },
                        "dtype": "compas.geometry/Box",
                        "guid": "1ad189c7-5ee3-4223-b48c-9ee081a7e131"
                    },
                    "attributes": {},
                    "collision_mesh": {
                        "data": {
                            "attributes": {},
                            "default_edge_attributes": {},
                            "default_face_attributes": {},
                            "default_vertex_attributes": {
                                "x": 0.0,
                                "y": 0.0,
                                "z": 0.0
                            },
                            "edgedata": {},
                            "face": {
                                "0": [
                                    0,
                                    2,
                                    1
                                ],
                                "1": [
                                    0,
                                    1,
                                    3
                                ],
                                "2": [
                                    1,
                                    2,
                                    3
                                ],
                                "3": [
                                    2,
                                    0,
                                    3
                                ]
                            },
                            "facedata": {
                                "0": {},
                                "1": {},
                                "2": {},
                                "3": {}
                            },
                            "max_face": 3,
                            "max_vertex": 3,
                            "vertex": {
                                "0": {
                                    "x": -0.8164965809277261,
                                    "y": 0.0,
                                    "z": -0.5773502691896258
                                },
                                "1": {
                                    "x": 0.0,
                                    "y": -0.8164965809277261,
                                    "z": 0.5773502691896258
                                },
                                "2": {
                                    "x": 0.8164965809277261,
                                    "y": 0.0,
                                    "z": -0.5773502691896258
                                },
                                "3": {
                                    "x": 0.0,
                                    "y": 0.8164965809277261,
                                    "z": 0.5773502691896258
                                }
                            }
                        },
                        "dtype": "compas.datastructures/Mesh",
                        "guid": "caa2d40e-8b69-4129-ad7e-b2fd0bee7b12"
                    },
                    "dimensions": [
                        1.6329931618554523,
                        1.1547005383792517,
                        1.6329931618554523
                    ],
                    "face_polygons": [],
                    "features": {},
                    "frame": {
                        "data": {
                            "point": [
                                0.0,
                                0.0,
                                0.0
                            ],
                            "xaxis": [
                                1.0,
                                0.0,
                                0.0
                            ],
                            "yaxis": [
                                0.0,
                                1.0,
                                0.0
                            ]
                        },
                        "dtype": "compas.geometry/Frame",
                        "guid": "7ac8d5f0-a803-417e-b4c1-d24b0a186a9e",
                        "name": "Frame"
                    },
                    "geometry": {
                        "data": {
                            "attributes": {},
                            "default_edge_attributes": {},
                            "default_face_attributes": {},
                            "default_vertex_attributes": {
                                "x": 0.0,
                                "y": 0.0,
                                "z": 0.0
                            },
                            "edgedata": {},
                            "face": {
                                "0": [
                                    0,
                                    1,
                                    2
                                ],
                                "1": [
                                    0,
                                    3,
                                    1
                                ],
                                "2": [
                                    0,
                                    2,
                                    3
                                ],
                                "3": [
                                    1,
                                    3,
                                    2
                                ]
                            },
                            "facedata": {
                                "0": {},
                                "1": {},
                                "2": {},
                                "3": {}
                            },
                            "max_face": 3,
                            "max_vertex": 3,
                            "vertex": {
                                "0": {
                                    "x": -0.8164965809277261,
                                    "y": 0.0,
                                    "z": -0.5773502691896258
                                },
                                "1": {
                                    "x": 0.0,
                                    "y": -0.8164965809277261,
                                    "z": 0.5773502691896258
                                },
                                "2": {
                                    "x": 0.8164965809277261,
                                    "y": 0.0,
                                    "z": -0.5773502691896258
                                },
                                "3": {
                                    "x": 0.0,
                                    "y": 0.8164965809277261,
                                    "z": 0.5773502691896258
                                }
                            }
                        },
                        "dtype": "compas.datastructures/Mesh",
                        "guid": "92f12770-68a0-4341-9569-c6693385cc06",
                        "name": "Mesh"
                    },
                    "geometry_simplified": {
                        "data": [
                            0.0,
                            0.0,
                            0.0
                        ],
                        "dtype": "compas.geometry/Point",
                        "guid": "5afa1254-a284-4211-86ac-546bd849b092",
                        "name": "Point"
                    },
                    "insertion": {
                        "data": [
                            0.0,
                            0.0,
                            -1.0
                        ],
                        "dtype": "compas.geometry/Vector",
                        "guid": "cac8af49-0ccd-4217-bd4a-42e03c7b10c1"
                    },
                    "name": "Block",
                    "obb": {
                        "data": {
                            "frame": {
                                "point": [
                                    0.1360827634879544,
                                    0.0,
                                    -0.3849001794597505
                                ],
                                "xaxis": [
                                    1.0,
                                    0.0,
                                    0.0
                                ],
                                "yaxis": [
                                    0.0,
                                    1.0,
                                    0.0
                                ]
                            },
                            "xsize": 1.905158688831361,
                            "ysize": 1.6329931618554523,
                            "zsize": 1.9245008972987527
                        },
                        "dtype": "compas.geometry/Box",
                        "guid": "d1d07ae0-7386-4d90-a947-db0c36a998ae"
                    }
                },
                "dtype": "compas_model.elements/Block",
                "guid": "0ef49b6e-bdcc-424f-9776-f97eed894cf4"
            },
            "2dd11301-b300-4c03-b5ca-49274f78518e": {
                "data": {
                    "aabb": {
                        "data": {
                            "frame": {
                                "point": [
                                    0.0,
                                    0.0,
                                    -5.551115123125783e-17
                                ],
                                "xaxis": [
                                    1.0,
                                    0.0,
                                    0.0
                                ],
                                "yaxis": [
                                    0.0,
                                    1.0,
                                    0.0
                                ]
                            },
                            "xsize": 2.3094010767585034,
                            "ysize": 2.3094010767585034,
                            "zsize": 2.3094010767585034
                        },
                        "dtype": "compas.geometry/Box",
                        "guid": "1439138e-d475-4efc-9a24-658331dec688"
                    },
                    "attributes": {},
                    "collision_mesh": {
                        "data": {
                            "attributes": {},
                            "default_edge_attributes": {},
                            "default_face_attributes": {},
                            "default_vertex_attributes": {
                                "x": 0.0,
                                "y": 0.0,
                                "z": 0.0
                            },
                            "edgedata": {},
                            "face": {
                                "0": [
                                    0,
                                    2,
                                    1
                                ],
                                "1": [
                                    2,
                                    0,
                                    3
                                ],
                                "10": [
                                    5,
                                    6,
                                    7
                                ],
                                "11": [
                                    6,
                                    0,
                                    7
                                ],
                                "2": [
                                    4,
                                    2,
                                    5
                                ],
                                "3": [
                                    2,
                                    3,
                                    5
                                ],
                                "4": [
                                    3,
                                    0,
                                    6
                                ],
                                "5": [
                                    5,
                                    3,
                                    6
                                ],
                                "6": [
                                    0,
                                    1,
                                    7
                                ],
                                "7": [
                                    2,
                                    4,
                                    7
                                ],
                                "8": [
                                    1,
                                    2,
                                    7
                                ],
                                "9": [
                                    4,
                                    5,
                                    7
                                ]
                            },
                            "facedata": {
                                "0": {},
                                "1": {},
                                "10": {},
                                "11": {},
                                "2": {},
                                "3": {},
                                "4": {},
                                "5": {},
                                "6": {},
                                "7": {},
                                "8": {},
                                "9": {}
                            },
                            "max_face": 11,
                            "max_vertex": 7,
                            "vertex": {
                                "0": {
                                    "x": -1.1547005383792517,
                                    "y": -1.1547005383792517,
                                    "z": -1.1547005383792517
                                },
                                "1": {
                                    "x": 1.1547005383792517,
                                    "y": -1.1547005383792517,
                                    "z": -1.1547005383792517
                                },
                                "2": {
                                    "x": 1.1547005383792517,
                                    "y": 1.1547005383792517,
                                    "z": -1.1547005383792517
                                },
                                "3": {
                                    "x": -1.1547005383792517,
                                    "y": 1.1547005383792517,
                                    "z": -1.1547005383792517
                                },
                                "4": {
                                    "x": 1.1547005383792517,
                                    "y": 1.1547005383792517,
                                    "z": 1.1547005383792517
                                },
                                "5": {
                                    "x": -1.1547005383792517,
                                    "y": 1.1547005383792517,
                                    "z": 1.1547005383792517
                                },
                                "6": {
                                    "x": -1.1547005383792517,
                                    "y": -1.1547005383792517,
                                    "z": 1.1547005383792517
                                },
                                "7": {
                                    "x": 1.1547005383792517,
                                    "y": -1.1547005383792517,
                                    "z": 1.1547005383792517
                                }
                            }
                        },
                        "dtype": "compas.datastructures/Mesh",
                        "guid": "34dcf176-7c26-455e-845c-9c00250eb4ef"
                    },
                    "dimensions": [
                        2.3094010767585034,
                        2.3094010767585034,
                        2.3094010767585034
                    ],
                    "face_polygons": [],
                    "features": {},
                    "frame": {
                        "data": {
                            "point": [
                                0.0,
                                0.0,
                                0.0
                            ],
                            "xaxis": [
                                1.0,
                                0.0,
                                0.0
                            ],
                            "yaxis": [
                                0.0,
                                1.0,
                                0.0
                            ]
                        },
                        "dtype": "compas.geometry/Frame",
                        "guid": "8588bbce-e217-4eb4-8ef8-4de1fbf6c263",
                        "name": "Frame"
                    },
                    "geometry": {
                        "data": {
                            "attributes": {},
                            "default_edge_attributes": {},
                            "default_face_attributes": {},
                            "default_vertex_attributes": {
                                "x": 0.0,
                                "y": 0.0,
                                "z": 0.0
                            },
                            "edgedata": {},
                            "face": {
                                "0": [
                                    0,
                                    3,
                                    2,
                                    1
                                ],
                                "1": [
                                    0,
                                    1,
                                    7,
                                    6
                                ],
                                "2": [
                                    0,
                                    6,
                                    5,
                                    3
                                ],
                                "3": [
                                    4,
                                    2,
                                    3,
                                    5
                                ],
                                "4": [
                                    4,
                                    7,
                                    1,
                                    2
                                ],
                                "5": [
                                    4,
                                    5,
                                    6,
                                    7
                                ]
                            },
                            "facedata": {
                                "0": {},
                                "1": {},
                                "2": {},
                                "3": {},
                                "4": {},
                                "5": {}
                            },
                            "max_face": 5,
                            "max_vertex": 7,
                            "vertex": {
                                "0": {
                                    "x": -1.1547005383792517,
                                    "y": -1.1547005383792517,
                                    "z": -1.1547005383792517
                                },
                                "1": {
                                    "x": 1.1547005383792517,
                                    "y": -1.1547005383792517,
                                    "z": -1.1547005383792517
                                },
                                "2": {
                                    "x": 1.1547005383792517,
                                    "y": 1.1547005383792517,
                                    "z": -1.1547005383792517
                                },
                                "3": {
                                    "x": -1.1547005383792517,
                                    "y": 1.1547005383792517,
                                    "z": -1.1547005383792517
                                },
                                "4": {
                                    "x": 1.1547005383792517,
                                    "y": 1.1547005383792517,
                                    "z": 1.1547005383792517
                                },
                                "5": {
                                    "x": -1.1547005383792517,
                                    "y": 1.1547005383792517,
                                    "z": 1.1547005383792517
                                },
                                "6": {
                                    "x": -1.1547005383792517,
                                    "y": -1.1547005383792517,
                                    "z": 1.1547005383792517
                                },
                                "7": {
                                    "x": 1.1547005383792517,
                                    "y": -1.1547005383792517,
                                    "z": 1.1547005383792517
                                }
                            }
                        },
                        "dtype": "compas.datastructures/Mesh",
                        "guid": "c862ec49-12a5-4857-bf7c-75cbfe4720d9",
                        "name": "Mesh"
                    },
                    "geometry_simplified": {
                        "data": [
                            0.0,
                            0.0,
                            0.0
                        ],
                        "dtype": "compas.geometry/Point",
                        "guid": "4573483c-a364-4839-a913-461083cd23e4",
                        "name": "Point"
                    },
                    "insertion": {
                        "data": [
                            0.0,
                            0.0,
                            -1.0
                        ],
                        "dtype": "compas.geometry/Vector",
                        "guid": "34721a37-9d8d-460d-a899-af01e8a09347"
                    },
                    "name": "Block",
                    "obb": {
                        "data": {
                            "frame": {
                                "point": [
                                    0.0,
                                    0.0,
                                    -5.551115123125783e-17
                                ],
                                "xaxis": [
                                    1.0,
                                    0.0,
                                    0.0
                                ],
                                "yaxis": [
                                    0.0,
                                    1.0,
                                    0.0
                                ]
                            },
                            "xsize": 2.3094010767585034,
                            "ysize": 2.3094010767585034,
                            "zsize": 2.3094010767585034
                        },
                        "dtype": "compas.geometry/Box",
                        "guid": "5a47a43e-52b3-4812-af94-ab520ab9eeae"
                    }
                },
                "dtype": "compas_model.elements/Block",
                "guid": "2dd11301-b300-4c03-b5ca-49274f78518e"
            },
            "ac91a02c-06ba-4feb-beca-0855ff350088": {
                "data": {
                    "aabb": {
                        "data": {
                            "frame": {
                                "point": [
                                    0.0,
                                    0.0,
                                    2.7755575615628914e-17
                                ],
                                "xaxis": [
                                    1.0,
                                    0.0,
                                    0.0
                                ],
                                "yaxis": [
                                    0.0,
                                    1.0,
                                    0.0
                                ]
                            },
                            "xsize": 1.9999999999999996,
                            "ysize": 1.9999999999999996,
                            "zsize": 1.9999999999999996
                        },
                        "dtype": "compas.geometry/Box",
                        "guid": "99bf039d-4ae2-48d7-a939-f886123ff189"
                    },
                    "attributes": {},
                    "collision_mesh": {
                        "data": {
                            "attributes": {},
                            "default_edge_attributes": {},
                            "default_face_attributes": {},
                            "default_vertex_attributes": {
                                "x": 0.0,
                                "y": 0.0,
                                "z": 0.0
                            },
                            "edgedata": {},
                            "face": {
                                "0": [
                                    0,
                                    2,
                                    1
                                ],
                                "1": [
                                    1,
                                    2,
                                    3
                                ],
                                "2": [
                                    3,
                                    2,
                                    4
                                ],
                                "3": [
                                    2,
                                    0,
                                    4
                                ],
                                "4": [
                                    0,
                                    1,
                                    5
                                ],
                                "5": [
                                    4,
                                    0,
                                    5
                                ],
                                "6": [
                                    1,
                                    3,
                                    5
                                ],
                                "7": [
                                    3,
                                    4,
                                    5
                                ]
                            },
                            "facedata": {
                                "0": {},
                                "1": {},
                                "2": {},
                                "3": {},
                                "4": {},
                                "5": {},
                                "6": {},
                                "7": {}
                            },
                            "max_face": 7,
                            "max_vertex": 5,
                            "vertex": {
                                "0": {
                                    "x": -0.9999999999999998,
                                    "y": 0.0,
                                    "z": 0.0
                                },
                                "1": {
                                    "x": 0.0,
                                    "y": -0.9999999999999998,
                                    "z": 0.0
                                },
                                "2": {
                                    "x": 0.0,
                                    "y": 0.0,
                                    "z": -0.9999999999999998
                                },
                                "3": {
                                    "x": 0.9999999999999998,
                                    "y": 0.0,
                                    "z": 0.0
                                },
                                "4": {
                                    "x": 0.0,
                                    "y": 0.9999999999999998,
                                    "z": 0.0
                                },
                                "5": {
                                    "x": 0.0,
                                    "y": 0.0,
                                    "z": 0.9999999999999998
                                }
                            }
                        },
                        "dtype": "compas.datastructures/Mesh",
                        "guid": "a0e93901-8a73-4d02-b09c-15a5fc3c9646"
                    },
                    "dimensions": [
                        1.9999999999999996,
                        1.9999999999999996,
                        1.9999999999999996
                    ],
                    "face_polygons": [],
                    "features": {},
                    "frame": {
                        "data": {
                            "point": [
                                0.0,
                                0.0,
                                1.6024689053196374e-17
                            ],
                            "xaxis": [
                                1.0,
                                0.0,
                                0.0
                            ],
                            "yaxis": [
                                0.0,
                                1.0,
                                0.0
                            ]
                        },
                        "dtype": "compas.geometry/Frame",
                        "guid": "d720d600-fc4f-45e8-8bb6-01ed56f18070",
                        "name": "Frame"
                    },
                    "geometry": {
                        "data": {
                            "attributes": {},
                            "default_edge_attributes": {},
                            "default_face_attributes": {},
                            "default_vertex_attributes": {
                                "x": 0.0,
                                "y": 0.0,
                                "z": 0.0
                            },
                            "edgedata": {},
                            "face": {
                                "0": [
                                    0,
                                    1,
                                    5
                                ],
                                "1": [
                                    1,
                                    3,
                                    5
                                ],
                                "2": [
                                    3,
                                    4,
                                    5
                                ],
                                "3": [
                                    0,
                                    5,
                                    4
                                ],
                                "4": [
                                    0,
                                    2,
                                    1
                                ],
                                "5": [
                                    1,
                                    2,
                                    3
                                ],
                                "6": [
                                    3,
                                    2,
                                    4
                                ],
                                "7": [
                                    0,
                                    4,
                                    2
                                ]
                            },
                            "facedata": {
                                "0": {},
                                "1": {},
                                "2": {},
                                "3": {},
                                "4": {},
                                "5": {},
                                "6": {},
                                "7": {}
                            },
                            "max_face": 7,
                            "max_vertex": 5,
                            "vertex": {
                                "0": {
                                    "x": -0.9999999999999998,
                                    "y": 0.0,
                                    "z": 0.0
                                },
                                "1": {
                                    "x": 0.0,
                                    "y": -0.9999999999999998,
                                    "z": 0.0
                                },
                                "2": {
                                    "x": 0.0,
                                    "y": 0.0,
                                    "z": -0.9999999999999998
                                },
                                "3": {
                                    "x": 0.9999999999999998,
                                    "y": 0.0,
                                    "z": 0.0
                                },
                                "4": {
                                    "x": 0.0,
                                    "y": 0.9999999999999998,
                                    "z": 0.0
                                },
                                "5": {
                                    "x": 0.0,
                                    "y": 0.0,
                                    "z": 0.9999999999999998
                                }
                            }
                        },
                        "dtype": "compas.datastructures/Mesh",
                        "guid": "ecee0ff3-7677-441a-885a-3cb1dea93245",
                        "name": "Mesh"
                    },
                    "geometry_simplified": {
                        "data": [
                            0.0,
                            0.0,
                            1.6024689053196374e-17
                        ],
                        "dtype": "compas.geometry/Point",
                        "guid": "5a4622a7-3ccf-4b01-98ca-b5b454faae7b",
                        "name": "Point"
                    },
                    "insertion": {
                        "data": [
                            0.0,
                            0.0,
                            -1.0
                        ],
                        "dtype": "compas.geometry/Vector",
                        "guid": "1bed1f41-929e-458b-92b3-5c728bdd5cce"
                    },
                    "name": "Block",
                    "obb": {
                        "data": {
                            "frame": {
                                "point": [
                                    -4.163336342344337e-17,
                                    0.0,
                                    -1.6653345369377348e-16
                                ],
                                "xaxis": [
                                    1.0,
                                    0.0,
                                    0.0
                                ],
                                "yaxis": [
                                    0.0,
                                    1.0,
                                    0.0
                                ]
                            },
                            "xsize": 1.9999999999999996,
                            "ysize": 2.333333333333333,
                            "zsize": 2.333333333333333
                        },
                        "dtype": "compas.geometry/Box",
                        "guid": "9962b2b6-2b48-414e-ac35-e2304983eecb"
                    }
                },
                "dtype": "compas_model.elements/Block",
                "guid": "ac91a02c-06ba-4feb-beca-0855ff350088"
            }
        },
        "hierarchy": {
            "name": "model",
            "nodes": [
                {
                    "children": [
                        {
                            "children": [
                                {
                                    "element": {
                                        "data": {
                                            "aabb": {
                                                "data": {
                                                    "frame": {
                                                        "point": [
                                                            0.0,
                                                            0.0,
                                                            -2.7755575615628914e-17
                                                        ],
                                                        "xaxis": [
                                                            1.0,
                                                            0.0,
                                                            0.0
                                                        ],
                                                        "yaxis": [
                                                            0.0,
                                                            1.0,
                                                            0.0
                                                        ]
                                                    },
                                                    "xsize": 1.6329931618554523,
                                                    "ysize": 1.6329931618554523,
                                                    "zsize": 1.1547005383792517
                                                },
                                                "dtype": "compas.geometry/Box",
                                                "guid": "1ad189c7-5ee3-4223-b48c-9ee081a7e131"
                                            },
                                            "attributes": {},
                                            "collision_mesh": {
                                                "data": {
                                                    "attributes": {},
                                                    "default_edge_attributes": {},
                                                    "default_face_attributes": {},
                                                    "default_vertex_attributes": {
                                                        "x": 0.0,
                                                        "y": 0.0,
                                                        "z": 0.0
                                                    },
                                                    "edgedata": {},
                                                    "face": {
                                                        "0": [
                                                            0,
                                                            2,
                                                            1
                                                        ],
                                                        "1": [
                                                            0,
                                                            1,
                                                            3
                                                        ],
                                                        "2": [
                                                            1,
                                                            2,
                                                            3
                                                        ],
                                                        "3": [
                                                            2,
                                                            0,
                                                            3
                                                        ]
                                                    },
                                                    "facedata": {
                                                        "0": {},
                                                        "1": {},
                                                        "2": {},
                                                        "3": {}
                                                    },
                                                    "max_face": 3,
                                                    "max_vertex": 3,
                                                    "vertex": {
                                                        "0": {
                                                            "x": -0.8164965809277261,
                                                            "y": 0.0,
                                                            "z": -0.5773502691896258
                                                        },
                                                        "1": {
                                                            "x": 0.0,
                                                            "y": -0.8164965809277261,
                                                            "z": 0.5773502691896258
                                                        },
                                                        "2": {
                                                            "x": 0.8164965809277261,
                                                            "y": 0.0,
                                                            "z": -0.5773502691896258
                                                        },
                                                        "3": {
                                                            "x": 0.0,
                                                            "y": 0.8164965809277261,
                                                            "z": 0.5773502691896258
                                                        }
                                                    }
                                                },
                                                "dtype": "compas.datastructures/Mesh",
                                                "guid": "caa2d40e-8b69-4129-ad7e-b2fd0bee7b12"
                                            },
                                            "dimensions": [
                                                1.6329931618554523,
                                                1.1547005383792517,
                                                1.6329931618554523
                                            ],
                                            "face_polygons": [],
                                            "features": {},
                                            "frame": {
                                                "data": {
                                                    "point": [
                                                        0.0,
                                                        0.0,
                                                        0.0
                                                    ],
                                                    "xaxis": [
                                                        1.0,
                                                        0.0,
                                                        0.0
                                                    ],
                                                    "yaxis": [
                                                        0.0,
                                                        1.0,
                                                        0.0
                                                    ]
                                                },
                                                "dtype": "compas.geometry/Frame",
                                                "guid": "7ac8d5f0-a803-417e-b4c1-d24b0a186a9e",
                                                "name": "Frame"
                                            },
                                            "geometry": {
                                                "data": {
                                                    "attributes": {},
                                                    "default_edge_attributes": {},
                                                    "default_face_attributes": {},
                                                    "default_vertex_attributes": {
                                                        "x": 0.0,
                                                        "y": 0.0,
                                                        "z": 0.0
                                                    },
                                                    "edgedata": {},
                                                    "face": {
                                                        "0": [
                                                            0,
                                                            1,
                                                            2
                                                        ],
                                                        "1": [
                                                            0,
                                                            3,
                                                            1
                                                        ],
                                                        "2": [
                                                            0,
                                                            2,
                                                            3
                                                        ],
                                                        "3": [
                                                            1,
                                                            3,
                                                            2
                                                        ]
                                                    },
                                                    "facedata": {
                                                        "0": {},
                                                        "1": {},
                                                        "2": {},
                                                        "3": {}
                                                    },
                                                    "max_face": 3,
                                                    "max_vertex": 3,
                                                    "vertex": {
                                                        "0": {
                                                            "x": -0.8164965809277261,
                                                            "y": 0.0,
                                                            "z": -0.5773502691896258
                                                        },
                                                        "1": {
                                                            "x": 0.0,
                                                            "y": -0.8164965809277261,
                                                            "z": 0.5773502691896258
                                                        },
                                                        "2": {
                                                            "x": 0.8164965809277261,
                                                            "y": 0.0,
                                                            "z": -0.5773502691896258
                                                        },
                                                        "3": {
                                                            "x": 0.0,
                                                            "y": 0.8164965809277261,
                                                            "z": 0.5773502691896258
                                                        }
                                                    }
                                                },
                                                "dtype": "compas.datastructures/Mesh",
                                                "guid": "92f12770-68a0-4341-9569-c6693385cc06",
                                                "name": "Mesh"
                                            },
                                            "geometry_simplified": {
                                                "data": [
                                                    0.0,
                                                    0.0,
                                                    0.0
                                                ],
                                                "dtype": "compas.geometry/Point",
                                                "guid": "5afa1254-a284-4211-86ac-546bd849b092",
                                                "name": "Point"
                                            },
                                            "insertion": {
                                                "data": [
                                                    0.0,
                                                    0.0,
                                                    -1.0
                                                ],
                                                "dtype": "compas.geometry/Vector",
                                                "guid": "cac8af49-0ccd-4217-bd4a-42e03c7b10c1"
                                            },
                                            "name": "Block",
                                            "obb": {
                                                "data": {
                                                    "frame": {
                                                        "point": [
                                                            0.1360827634879544,
                                                            0.0,
                                                            -0.3849001794597505
                                                        ],
                                                        "xaxis": [
                                                            1.0,
                                                            0.0,
                                                            0.0
                                                        ],
                                                        "yaxis": [
                                                            0.0,
                                                            1.0,
                                                            0.0
                                                        ]
                                                    },
                                                    "xsize": 1.905158688831361,
                                                    "ysize": 1.6329931618554523,
                                                    "zsize": 1.9245008972987527
                                                },
                                                "dtype": "compas.geometry/Box",
                                                "guid": "d1d07ae0-7386-4d90-a947-db0c36a998ae"
                                            }
                                        },
                                        "dtype": "compas_model.elements/Block",
                                        "guid": "0ef49b6e-bdcc-424f-9776-f97eed894cf4"
                                    },
                                    "name": "spoke1"
                                },
                                {
                                    "element": {
                                        "data": {
                                            "aabb": {
                                                "data": {
                                                    "frame": {
                                                        "point": [
                                                            0.0,
                                                            0.0,
                                                            -5.551115123125783e-17
                                                        ],
                                                        "xaxis": [
                                                            1.0,
                                                            0.0,
                                                            0.0
                                                        ],
                                                        "yaxis": [
                                                            0.0,
                                                            1.0,
                                                            0.0
                                                        ]
                                                    },
                                                    "xsize": 2.3094010767585034,
                                                    "ysize": 2.3094010767585034,
                                                    "zsize": 2.3094010767585034
                                                },
                                                "dtype": "compas.geometry/Box",
                                                "guid": "1439138e-d475-4efc-9a24-658331dec688"
                                            },
                                            "attributes": {},
                                            "collision_mesh": {
                                                "data": {
                                                    "attributes": {},
                                                    "default_edge_attributes": {},
                                                    "default_face_attributes": {},
                                                    "default_vertex_attributes": {
                                                        "x": 0.0,
                                                        "y": 0.0,
                                                        "z": 0.0
                                                    },
                                                    "edgedata": {},
                                                    "face": {
                                                        "0": [
                                                            0,
                                                            2,
                                                            1
                                                        ],
                                                        "1": [
                                                            2,
                                                            0,
                                                            3
                                                        ],
                                                        "10": [
                                                            5,
                                                            6,
                                                            7
                                                        ],
                                                        "11": [
                                                            6,
                                                            0,
                                                            7
                                                        ],
                                                        "2": [
                                                            4,
                                                            2,
                                                            5
                                                        ],
                                                        "3": [
                                                            2,
                                                            3,
                                                            5
                                                        ],
                                                        "4": [
                                                            3,
                                                            0,
                                                            6
                                                        ],
                                                        "5": [
                                                            5,
                                                            3,
                                                            6
                                                        ],
                                                        "6": [
                                                            0,
                                                            1,
                                                            7
                                                        ],
                                                        "7": [
                                                            2,
                                                            4,
                                                            7
                                                        ],
                                                        "8": [
                                                            1,
                                                            2,
                                                            7
                                                        ],
                                                        "9": [
                                                            4,
                                                            5,
                                                            7
                                                        ]
                                                    },
                                                    "facedata": {
                                                        "0": {},
                                                        "1": {},
                                                        "10": {},
                                                        "11": {},
                                                        "2": {},
                                                        "3": {},
                                                        "4": {},
                                                        "5": {},
                                                        "6": {},
                                                        "7": {},
                                                        "8": {},
                                                        "9": {}
                                                    },
                                                    "max_face": 11,
                                                    "max_vertex": 7,
                                                    "vertex": {
                                                        "0": {
                                                            "x": -1.1547005383792517,
                                                            "y": -1.1547005383792517,
                                                            "z": -1.1547005383792517
                                                        },
                                                        "1": {
                                                            "x": 1.1547005383792517,
                                                            "y": -1.1547005383792517,
                                                            "z": -1.1547005383792517
                                                        },
                                                        "2": {
                                                            "x": 1.1547005383792517,
                                                            "y": 1.1547005383792517,
                                                            "z": -1.1547005383792517
                                                        },
                                                        "3": {
                                                            "x": -1.1547005383792517,
                                                            "y": 1.1547005383792517,
                                                            "z": -1.1547005383792517
                                                        },
                                                        "4": {
                                                            "x": 1.1547005383792517,
                                                            "y": 1.1547005383792517,
                                                            "z": 1.1547005383792517
                                                        },
                                                        "5": {
                                                            "x": -1.1547005383792517,
                                                            "y": 1.1547005383792517,
                                                            "z": 1.1547005383792517
                                                        },
                                                        "6": {
                                                            "x": -1.1547005383792517,
                                                            "y": -1.1547005383792517,
                                                            "z": 1.1547005383792517
                                                        },
                                                        "7": {
                                                            "x": 1.1547005383792517,
                                                            "y": -1.1547005383792517,
                                                            "z": 1.1547005383792517
                                                        }
                                                    }
                                                },
                                                "dtype": "compas.datastructures/Mesh",
                                                "guid": "34dcf176-7c26-455e-845c-9c00250eb4ef"
                                            },
                                            "dimensions": [
                                                2.3094010767585034,
                                                2.3094010767585034,
                                                2.3094010767585034
                                            ],
                                            "face_polygons": [],
                                            "features": {},
                                            "frame": {
                                                "data": {
                                                    "point": [
                                                        0.0,
                                                        0.0,
                                                        0.0
                                                    ],
                                                    "xaxis": [
                                                        1.0,
                                                        0.0,
                                                        0.0
                                                    ],
                                                    "yaxis": [
                                                        0.0,
                                                        1.0,
                                                        0.0
                                                    ]
                                                },
                                                "dtype": "compas.geometry/Frame",
                                                "guid": "8588bbce-e217-4eb4-8ef8-4de1fbf6c263",
                                                "name": "Frame"
                                            },
                                            "geometry": {
                                                "data": {
                                                    "attributes": {},
                                                    "default_edge_attributes": {},
                                                    "default_face_attributes": {},
                                                    "default_vertex_attributes": {
                                                        "x": 0.0,
                                                        "y": 0.0,
                                                        "z": 0.0
                                                    },
                                                    "edgedata": {},
                                                    "face": {
                                                        "0": [
                                                            0,
                                                            3,
                                                            2,
                                                            1
                                                        ],
                                                        "1": [
                                                            0,
                                                            1,
                                                            7,
                                                            6
                                                        ],
                                                        "2": [
                                                            0,
                                                            6,
                                                            5,
                                                            3
                                                        ],
                                                        "3": [
                                                            4,
                                                            2,
                                                            3,
                                                            5
                                                        ],
                                                        "4": [
                                                            4,
                                                            7,
                                                            1,
                                                            2
                                                        ],
                                                        "5": [
                                                            4,
                                                            5,
                                                            6,
                                                            7
                                                        ]
                                                    },
                                                    "facedata": {
                                                        "0": {},
                                                        "1": {},
                                                        "2": {},
                                                        "3": {},
                                                        "4": {},
                                                        "5": {}
                                                    },
                                                    "max_face": 5,
                                                    "max_vertex": 7,
                                                    "vertex": {
                                                        "0": {
                                                            "x": -1.1547005383792517,
                                                            "y": -1.1547005383792517,
                                                            "z": -1.1547005383792517
                                                        },
                                                        "1": {
                                                            "x": 1.1547005383792517,
                                                            "y": -1.1547005383792517,
                                                            "z": -1.1547005383792517
                                                        },
                                                        "2": {
                                                            "x": 1.1547005383792517,
                                                            "y": 1.1547005383792517,
                                                            "z": -1.1547005383792517
                                                        },
                                                        "3": {
                                                            "x": -1.1547005383792517,
                                                            "y": 1.1547005383792517,
                                                            "z": -1.1547005383792517
                                                        },
                                                        "4": {
                                                            "x": 1.1547005383792517,
                                                            "y": 1.1547005383792517,
                                                            "z": 1.1547005383792517
                                                        },
                                                        "5": {
                                                            "x": -1.1547005383792517,
                                                            "y": 1.1547005383792517,
                                                            "z": 1.1547005383792517
                                                        },
                                                        "6": {
                                                            "x": -1.1547005383792517,
                                                            "y": -1.1547005383792517,
                                                            "z": 1.1547005383792517
                                                        },
                                                        "7": {
                                                            "x": 1.1547005383792517,
                                                            "y": -1.1547005383792517,
                                                            "z": 1.1547005383792517
                                                        }
                                                    }
                                                },
                                                "dtype": "compas.datastructures/Mesh",
                                                "guid": "c862ec49-12a5-4857-bf7c-75cbfe4720d9",
                                                "name": "Mesh"
                                            },
                                            "geometry_simplified": {
                                                "data": [
                                                    0.0,
                                                    0.0,
                                                    0.0
                                                ],
                                                "dtype": "compas.geometry/Point",
                                                "guid": "4573483c-a364-4839-a913-461083cd23e4",
                                                "name": "Point"
                                            },
                                            "insertion": {
                                                "data": [
                                                    0.0,
                                                    0.0,
                                                    -1.0
                                                ],
                                                "dtype": "compas.geometry/Vector",
                                                "guid": "34721a37-9d8d-460d-a899-af01e8a09347"
                                            },
                                            "name": "Block",
                                            "obb": {
                                                "data": {
                                                    "frame": {
                                                        "point": [
                                                            0.0,
                                                            0.0,
                                                            -5.551115123125783e-17
                                                        ],
                                                        "xaxis": [
                                                            1.0,
                                                            0.0,
                                                            0.0
                                                        ],
                                                        "yaxis": [
                                                            0.0,
                                                            1.0,
                                                            0.0
                                                        ]
                                                    },
                                                    "xsize": 2.3094010767585034,
                                                    "ysize": 2.3094010767585034,
                                                    "zsize": 2.3094010767585034
                                                },
                                                "dtype": "compas.geometry/Box",
                                                "guid": "5a47a43e-52b3-4812-af94-ab520ab9eeae"
                                            }
                                        },
                                        "dtype": "compas_model.elements/Block",
                                        "guid": "2dd11301-b300-4c03-b5ca-49274f78518e"
                                    },
                                    "name": "spoke2"
                                },
                                {
                                    "element": {
                                        "data": {
                                            "aabb": {
                                                "data": {
                                                    "frame": {
                                                        "point": [
                                                            0.0,
                                                            0.0,
                                                            2.7755575615628914e-17
                                                        ],
                                                        "xaxis": [
                                                            1.0,
                                                            0.0,
                                                            0.0
                                                        ],
                                                        "yaxis": [
                                                            0.0,
                                                            1.0,
                                                            0.0
                                                        ]
                                                    },
                                                    "xsize": 1.9999999999999996,
                                                    "ysize": 1.9999999999999996,
                                                    "zsize": 1.9999999999999996
                                                },
                                                "dtype": "compas.geometry/Box",
                                                "guid": "99bf039d-4ae2-48d7-a939-f886123ff189"
                                            },
                                            "attributes": {},
                                            "collision_mesh": {
                                                "data": {
                                                    "attributes": {},
                                                    "default_edge_attributes": {},
                                                    "default_face_attributes": {},
                                                    "default_vertex_attributes": {
                                                        "x": 0.0,
                                                        "y": 0.0,
                                                        "z": 0.0
                                                    },
                                                    "edgedata": {},
                                                    "face": {
                                                        "0": [
                                                            0,
                                                            2,
                                                            1
                                                        ],
                                                        "1": [
                                                            1,
                                                            2,
                                                            3
                                                        ],
                                                        "2": [
                                                            3,
                                                            2,
                                                            4
                                                        ],
                                                        "3": [
                                                            2,
                                                            0,
                                                            4
                                                        ],
                                                        "4": [
                                                            0,
                                                            1,
                                                            5
                                                        ],
                                                        "5": [
                                                            4,
                                                            0,
                                                            5
                                                        ],
                                                        "6": [
                                                            1,
                                                            3,
                                                            5
                                                        ],
                                                        "7": [
                                                            3,
                                                            4,
                                                            5
                                                        ]
                                                    },
                                                    "facedata": {
                                                        "0": {},
                                                        "1": {},
                                                        "2": {},
                                                        "3": {},
                                                        "4": {},
                                                        "5": {},
                                                        "6": {},
                                                        "7": {}
                                                    },
                                                    "max_face": 7,
                                                    "max_vertex": 5,
                                                    "vertex": {
                                                        "0": {
                                                            "x": -0.9999999999999998,
                                                            "y": 0.0,
                                                            "z": 0.0
                                                        },
                                                        "1": {
                                                            "x": 0.0,
                                                            "y": -0.9999999999999998,
                                                            "z": 0.0
                                                        },
                                                        "2": {
                                                            "x": 0.0,
                                                            "y": 0.0,
                                                            "z": -0.9999999999999998
                                                        },
                                                        "3": {
                                                            "x": 0.9999999999999998,
                                                            "y": 0.0,
                                                            "z": 0.0
                                                        },
                                                        "4": {
                                                            "x": 0.0,
                                                            "y": 0.9999999999999998,
                                                            "z": 0.0
                                                        },
                                                        "5": {
                                                            "x": 0.0,
                                                            "y": 0.0,
                                                            "z": 0.9999999999999998
                                                        }
                                                    }
                                                },
                                                "dtype": "compas.datastructures/Mesh",
                                                "guid": "a0e93901-8a73-4d02-b09c-15a5fc3c9646"
                                            },
                                            "dimensions": [
                                                1.9999999999999996,
                                                1.9999999999999996,
                                                1.9999999999999996
                                            ],
                                            "face_polygons": [],
                                            "features": {},
                                            "frame": {
                                                "data": {
                                                    "point": [
                                                        0.0,
                                                        0.0,
                                                        1.6024689053196374e-17
                                                    ],
                                                    "xaxis": [
                                                        1.0,
                                                        0.0,
                                                        0.0
                                                    ],
                                                    "yaxis": [
                                                        0.0,
                                                        1.0,
                                                        0.0
                                                    ]
                                                },
                                                "dtype": "compas.geometry/Frame",
                                                "guid": "d720d600-fc4f-45e8-8bb6-01ed56f18070",
                                                "name": "Frame"
                                            },
                                            "geometry": {
                                                "data": {
                                                    "attributes": {},
                                                    "default_edge_attributes": {},
                                                    "default_face_attributes": {},
                                                    "default_vertex_attributes": {
                                                        "x": 0.0,
                                                        "y": 0.0,
                                                        "z": 0.0
                                                    },
                                                    "edgedata": {},
                                                    "face": {
                                                        "0": [
                                                            0,
                                                            1,
                                                            5
                                                        ],
                                                        "1": [
                                                            1,
                                                            3,
                                                            5
                                                        ],
                                                        "2": [
                                                            3,
                                                            4,
                                                            5
                                                        ],
                                                        "3": [
                                                            0,
                                                            5,
                                                            4
                                                        ],
                                                        "4": [
                                                            0,
                                                            2,
                                                            1
                                                        ],
                                                        "5": [
                                                            1,
                                                            2,
                                                            3
                                                        ],
                                                        "6": [
                                                            3,
                                                            2,
                                                            4
                                                        ],
                                                        "7": [
                                                            0,
                                                            4,
                                                            2
                                                        ]
                                                    },
                                                    "facedata": {
                                                        "0": {},
                                                        "1": {},
                                                        "2": {},
                                                        "3": {},
                                                        "4": {},
                                                        "5": {},
                                                        "6": {},
                                                        "7": {}
                                                    },
                                                    "max_face": 7,
                                                    "max_vertex": 5,
                                                    "vertex": {
                                                        "0": {
                                                            "x": -0.9999999999999998,
                                                            "y": 0.0,
                                                            "z": 0.0
                                                        },
                                                        "1": {
                                                            "x": 0.0,
                                                            "y": -0.9999999999999998,
                                                            "z": 0.0
                                                        },
                                                        "2": {
                                                            "x": 0.0,
                                                            "y": 0.0,
                                                            "z": -0.9999999999999998
                                                        },
                                                        "3": {
                                                            "x": 0.9999999999999998,
                                                            "y": 0.0,
                                                            "z": 0.0
                                                        },
                                                        "4": {
                                                            "x": 0.0,
                                                            "y": 0.9999999999999998,
                                                            "z": 0.0
                                                        },
                                                        "5": {
                                                            "x": 0.0,
                                                            "y": 0.0,
                                                            "z": 0.9999999999999998
                                                        }
                                                    }
                                                },
                                                "dtype": "compas.datastructures/Mesh",
                                                "guid": "ecee0ff3-7677-441a-885a-3cb1dea93245",
                                                "name": "Mesh"
                                            },
                                            "geometry_simplified": {
                                                "data": [
                                                    0.0,
                                                    0.0,
                                                    1.6024689053196374e-17
                                                ],
                                                "dtype": "compas.geometry/Point",
                                                "guid": "5a4622a7-3ccf-4b01-98ca-b5b454faae7b",
                                                "name": "Point"
                                            },
                                            "insertion": {
                                                "data": [
                                                    0.0,
                                                    0.0,
                                                    -1.0
                                                ],
                                                "dtype": "compas.geometry/Vector",
                                                "guid": "1bed1f41-929e-458b-92b3-5c728bdd5cce"
                                            },
                                            "name": "Block",
                                            "obb": {
                                                "data": {
                                                    "frame": {
                                                        "point": [
                                                            -4.163336342344337e-17,
                                                            0.0,
                                                            -1.6653345369377348e-16
                                                        ],
                                                        "xaxis": [
                                                            1.0,
                                                            0.0,
                                                            0.0
                                                        ],
                                                        "yaxis": [
                                                            0.0,
                                                            1.0,
                                                            0.0
                                                        ]
                                                    },
                                                    "xsize": 1.9999999999999996,
                                                    "ysize": 2.333333333333333,
                                                    "zsize": 2.333333333333333
                                                },
                                                "dtype": "compas.geometry/Box",
                                                "guid": "9962b2b6-2b48-414e-ac35-e2304983eecb"
                                            }
                                        },
                                        "dtype": "compas_model.elements/Block",
                                        "guid": "ac91a02c-06ba-4feb-beca-0855ff350088"
                                    },
                                    "name": "spoke3"
                                }
                            ],
                            "geometry": {
                                "data": [
                                    0.0,
                                    0.0,
                                    0.0
                                ],
                                "dtype": "compas.geometry/Point",
                                "guid": "2154209f-5afb-4928-990f-b8ba27f4361c"
                            },
                            "name": "wheel"
                        }
                    ],
                    "geometry": null,
                    "name": "car"
                }
            ]
        },
        "interactions": {
            "attributes": {},
            "default_edge_attributes": {},
            "default_node_attributes": {
                "x": 0.0,
                "y": 0.0,
                "z": 0.0
            },
            "edge": {
                "'0ef49b6e-bdcc-424f-9776-f97eed894cf4'": {
                    "'2dd11301-b300-4c03-b5ca-49274f78518e'": {
                        "geometry": null,
                        "name": null,
                        "weight": 1
                    },
                    "'ac91a02c-06ba-4feb-beca-0855ff350088'": {
                        "geometry": null,
                        "name": null,
                        "weight": 1
                    }
                },
                "'2dd11301-b300-4c03-b5ca-49274f78518e'": {
                    "'ac91a02c-06ba-4feb-beca-0855ff350088'": {
                        "geometry": null,
                        "name": null,
                        "weight": 1
                    }
                },
                "'ac91a02c-06ba-4feb-beca-0855ff350088'": {}
            },
            "max_node": -1,
            "node": {
                "'0ef49b6e-bdcc-424f-9776-f97eed894cf4'": {},
                "'2dd11301-b300-4c03-b5ca-49274f78518e'": {},
                "'ac91a02c-06ba-4feb-beca-0855ff350088'": {}
            }
        },
        "name": "model"
    },
    "dtype": "compas_model.model/Model",
    "guid": "6947d762-d92f-4cb9-8ceb-d187bd7d78b2",
    "name": "model"
}